{"stat.walkOneCm":15688,"stat.boatOneCm":39084,"achievement.openInventory":46,"stat.horseOneCm":18351,"stat.leaveGame":2,"stat.mobKills":9,"stat.useItem.46":1,"stat.useItem.69":1,"stat.useItem.383":205,"stat.flyOneCm":857935,"stat.drop":5,"stat.jump":36,"stat.swimOneCm":6241,"stat.playOneMinute":82266,"achievement.exploreAllBiomes":{"value":0,"progress":["Sunflower Plains","ForestHills","Roofed Forest","Birch Forest","Plains","TaigaHills","Beach","Extreme Hills+","River","Forest","Ocean","Taiga","Extreme Hills","Deep Ocean"]},"stat.diveOneCm":25049}